calign/__init__.py
calign/core.py
calign-1.0.1.dist-info/licenses/LICENCE
tests/__init__.py
calign-1.0.1.dist-info/METADATA
calign-1.0.1.dist-info/WHEEL
calign-1.0.1.dist-info/top_level.txt
calign-1.0.1.dist-info/RECORD
