Metadata-Version: 2.4
Name: calign
Version: 1.0.1
Summary: A Python package for aligning epitopes to protein sequences
Home-page: https://github.com/labiomol/Calign-development
Author: André Luiz Caliari Costa, Leonardo Pereira de Araújo, Evandro Neves Silva, Patrícia Paiva Corsetti, Leonardo Augusto de Almeida
Author-email: André Luiz Caliari Costa <alcc.biology@gmail.com>, André Luiz Caliari Costa <andre.costa@sou.unifal-mg.edu.br>, Leonardo Pereira de Araújo <leonardo.araujo@sou.unifal-mg.edu.br>, Evandro Neves Silva <evandro.silva@sou.unifal-mg.edu.br>, Patrícia Paiva Corsetti <patricia.corsetti@unifal-mg.edu.br>, Leonardo Augusto de Almeida <leonardo.almeida@unifal-mg.edu.br>
License: MIT
Project-URL: Homepage, https://github.com/labiomol/Calign-development
Project-URL: Documentation, https://github.com/labiomol/Calign-development/blob/main/README.md
Project-URL: Repository, https://github.com/labiomol/Calign-development
Project-URL: Issues, https://github.com/labiomol/Calign-development/issues
Keywords: bioinformatics,epitope,alignment,protein,sequence
Classifier: Development Status :: 4 - Beta
Classifier: Intended Audience :: Science/Research
Classifier: Topic :: Scientific/Engineering :: Bio-Informatics
Classifier: License :: OSI Approved :: MIT License
Classifier: Programming Language :: Python :: 3
Classifier: Programming Language :: Python :: 3.8
Classifier: Programming Language :: Python :: 3.9
Classifier: Programming Language :: Python :: 3.10
Classifier: Programming Language :: Python :: 3.11
Classifier: Programming Language :: Python :: 3.12
Requires-Python: >=3.8
License-File: LICENCE
Requires-Dist: numpy>=1.20.0
Requires-Dist: biopython>=1.79
Requires-Dist: matplotlib>=3.3.0
Dynamic: author
Dynamic: home-page
Dynamic: license-file
Dynamic: requires-python
